{"dealId":"da660b70-0d3a-4856-9a71-5b322a1d6883","at":"2026-01-15T18:19:48.547Z","projection":{"state":"Operating","stressMode":"SM-0"},"approvals":{"OPEN_REVIEW":{"threshold":1,"satisfiedByRole":{},"satisfied":false},"APPROVE_DEAL":{"threshold":1,"satisfiedByRole":{},"satisfied":false},"ATTEST_READY_TO_CLOSE":{"threshold":2,"satisfiedByRole":{},"satisfied":false},"FINALIZE_CLOSING":{"threshold":3,"satisfiedByRole":{},"satisfied":false},"ACTIVATE_OPERATIONS":{"threshold":2,"satisfiedByRole":{},"satisfied":false},"DECLARE_CHANGE":{"threshold":1,"satisfiedByRole":{},"satisfied":false},"RECONCILE_CHANGE":{"threshold":2,"satisfiedByRole":{},"satisfied":false},"DECLARE_DISTRESS":{"threshold":1,"satisfiedByRole":{},"satisfied":false},"RESOLVE_DISTRESS":{"threshold":2,"satisfiedByRole":{},"satisfied":false},"IMPOSE_FREEZE":{"threshold":1,"satisfiedByRole":{},"satisfied":false},"LIFT_FREEZE":{"threshold":1,"satisfiedByRole":{},"satisfied":false},"FINALIZE_EXIT":{"threshold":1,"satisfiedByRole":{},"satisfied":false},"TERMINATE_DEAL":{"threshold":1,"satisfiedByRole":{},"satisfied":false},"DISPUTE_DATA":{"threshold":1,"satisfiedByRole":{},"satisfied":false},"OVERRIDE":{"threshold":1,"satisfiedByRole":{},"satisfied":false}},"materials":{"list":[],"requiredFor":{"APPROVE_DEAL":[{"type":"UnderwritingSummary","requiredTruth":"HUMAN","currentTruth":null,"status":"MISSING"}],"ATTEST_READY_TO_CLOSE":[{"type":"FinalUnderwriting","requiredTruth":"DOC","currentTruth":null,"status":"MISSING"},{"type":"SourcesAndUses","requiredTruth":"DOC","currentTruth":null,"status":"MISSING"}],"FINALIZE_CLOSING":[{"type":"WireConfirmation","requiredTruth":"DOC","currentTruth":null,"status":"MISSING"},{"type":"EntityFormationDocs","requiredTruth":"DOC","currentTruth":null,"status":"MISSING"}],"ACTIVATE_OPERATIONS":[{"type":"PropertyManagementAgreement","requiredTruth":"DOC","currentTruth":null,"status":"MISSING"}]}},"timeline":{"eventsCount":26,"lastEventAt":"2026-01-14T15:53:13.825Z","lastEventType":"ChangeReconciled"},"integrity":{"replayFrom":"events+materials","deterministic":true}}